tests/__init__.py
tests/test1.py
tests/testin.py
elecu-0.0.2.dist-info/LICENSE.TXT
elecu-0.0.2.dist-info/METADATA
elecu-0.0.2.dist-info/WHEEL
elecu-0.0.2.dist-info/top_level.txt
elecu-0.0.2.dist-info/RECORD
