Metadata-Version: 2.1
Name: elecu
Version: 0.0.2
Summary: ELE is a Python-based open-source project designed to enhance 
Home-page: https://github.com/kris-aid/ELECU
Author: Kristian Mendoza
License: GPL-3.0
Project-URL: Documentation, https://kris-aid.github.io/ELECU/
Keywords: Ecuador,elections,CNE
Classifier: Development Status :: 2 - Pre-Alpha
Classifier: Topic :: Utilities
Classifier: License :: OSI Approved :: GNU General Public License v3 (GPLv3)
Classifier: Natural Language :: Spanish
Classifier: Programming Language :: Python :: 3
License-File: LICENSE.TXT
Requires-Dist: pandas
Requires-Dist: numpy
Requires-Dist: matplotlib
Requires-Dist: seaborn
Requires-Dist: unidecode
